{
    "lan": ["vi", "en"],
    "default": "vi",
    "data": {
      "title": {
        "vi": "X E P H I N H",
        "en": "T E T R I S"
      },
      "github": {
        "vi": "GitHub",
        "en": "GitHub"
      },
      "linkTitle": {
        "vi": "Nguon DL",
        "en": "View data source"
      },
      "QRCode":{
        "vi": "mã QR ",
        "en": "QR code"
      },
      "titleCenter": {
        "vi": "XEP HINH CO DIEN",
        "en": "TETRIS"
      },
      "point": {
        "vi": "Điểm",
        "en": "Point"
      },
      "highestScore": {
        "vi": "Tối đa",
        "en": "Max"
      },
      "lastRound": {
        "vi": "Màn cuối",
        "en": "Last Round"
      },
      "cleans": {
        "vi": "Xóa",
        "en": "Cleans"
      },
      "level": {
        "vi": "Mức độ",
        "en": "Level"
      },
      "startLine": {
        "vi": "Dòng bắt đầu",
        "en": "Start Line"
      },
      "next": {
        "vi": "Tiếp tục",
        "en": "Next"
      },
      "pause": {
        "vi": "Tạm dừng",
        "en": "Pause"
      },
      "sound": {
        "vi": "Âm thanh",
        "en": "Sound"
      },
      "reset": {
        "vi": "Reset",
        "en": "Reset"
      },
      "rotation": {
        "vi": "Xoay",
        "en": "Rotation"
      },
      "left": {
        "vi": "Trái",
        "en": "Left"
      },
      "right": {
        "vi": "Phải",
        "en": "Right"
      },
      "down": {
        "vi": "Xuống",
        "en": "Down"
      },
      "drop": {
        "vi": "Thả",
        "en": "Drop"
      }
    }
  }
  